zpp_flow/__init__.py
zpp_flow/cli.py
zpp_flow/console.py
zpp_flow/app/logs.py
zpp_flow/core/decorator.py
zpp_flow/core/main.py
zpp_flow/core/runner.py
zpp_flow/core/structure.py
zpp_flow/core/vault.py
zpp_flow/core/sandbox/env.py
zpp_flow/core/sandbox/package.py
zpp_flow/core/sandbox/sandbox.py
zpp_flow/internal_fabric/analyse.py
zpp_flow/internal_fabric/fabric.py
zpp_flow-1.4.1.dist-info/licenses/LICENSE
zpp_flow-1.4.1.dist-info/METADATA
zpp_flow-1.4.1.dist-info/WHEEL
zpp_flow-1.4.1.dist-info/entry_points.txt
zpp_flow-1.4.1.dist-info/top_level.txt
zpp_flow-1.4.1.dist-info/RECORD
