Metadata-Version: 2.4
Name: zpp_flow
Version: 1.4.1
Summary: système d'exécution de task
Author: 
License: mit
Platform: ALL
License-File: LICENSE
Requires-Dist: zpp_args
Requires-Dist: zpp_color
Requires-Dist: zpp_config
Requires-Dist: impmagic
Requires-Dist: keyring
Requires-Dist: keyrings.alt
Requires-Dist: zpp_store
Requires-Dist: cryptography
Dynamic: description
Dynamic: description-content-type
Dynamic: keywords
Dynamic: license
Dynamic: license-file
Dynamic: platform
Dynamic: requires-dist
Dynamic: summary
